lockout/__init__.py
lockout/core.py
lockout/pytorch_utils.py
lockout/utils.py
lockout-0.1.5.dist-info/LICENSE
lockout-0.1.5.dist-info/WHEEL
lockout-0.1.5.dist-info/METADATA
lockout-0.1.5.dist-info/RECORD
