Metadata-Version: 2.1
Name: lockout
Version: 0.1.5
Summary: Lockout: Sparse Regularization of Neural Networks
Home-page: https://github.com/warbelo/Lockout
Author: Wilmer Arbelo
Author-email: wilmer.arbelogonzalez@ucsf.edu
Requires-Dist: flit_core >=2,<4
Requires-Dist: scikit-learn
Requires-Dist: tqdm
Requires-Dist: pandas
Requires-Dist: matplotlib
Requires-Dist: numpy
